{"sections":{"main":{"type":"main-page","disabled":true,"settings":{"content_width":"80ch"}},"featured_collection_PDEMx6":{"type":"featured-collection","custom_css":[".h2 {font-size: 2.5rem;}"],"settings":{"collection":"beginner-audiophile-iems","products":[],"full_width":true,"stack_products":false,"show_progress_bar":false,"products_count":3,"products_per_row_mobile":"2","products_per_row_desktop":4,"subheading":"","title":"Beginner Audiophile IEMs","content":"","link_url":"","link_text":"","background":"","background_gradient":"","text_color":"","heading_color":"","heading_gradient":"","product_card_background":"","product_card_text_color":""}},"featured_collection_48GHWB":{"type":"featured-collection","custom_css":[".h2 {font-size: 2.5rem;}"],"settings":{"collection":"beginner-audiophile-headphones","products":[],"full_width":true,"stack_products":false,"show_progress_bar":false,"products_count":3,"products_per_row_mobile":"2","products_per_row_desktop":4,"subheading":"","title":"Beginner Audiophile Headphones","content":"","link_url":"","link_text":"","background":"","background_gradient":"","text_color":"","heading_color":"","heading_gradient":"","product_card_background":"","product_card_text_color":""}},"featured_collection_hMyJJk":{"type":"featured-collection","custom_css":[".h2 {font-size: 2.5rem;}"],"settings":{"collection":"portable-amps-dacs","products":[],"full_width":true,"stack_products":false,"show_progress_bar":false,"products_count":4,"products_per_row_mobile":"2","products_per_row_desktop":4,"subheading":"","title":"Portable Amps & DACs","content":"","link_url":"","link_text":"","background":"","background_gradient":"","text_color":"","heading_color":"","heading_gradient":"","product_card_background":"","product_card_text_color":""}},"featured_collection_eFH8UP":{"type":"featured-collection","custom_css":[".h2 {font-size: 2.5rem;}"],"settings":{"collection":"desktop-amps-dacs","products":[],"full_width":true,"stack_products":false,"show_progress_bar":false,"products_count":2,"products_per_row_mobile":"2","products_per_row_desktop":4,"subheading":"","title":"Desktop Amps & DACs","content":"","link_url":"","link_text":"","background":"","background_gradient":"","text_color":"","heading_color":"","heading_gradient":"","product_card_background":"","product_card_text_color":""}},"featured_collection_3EzJzq":{"type":"featured-collection","custom_css":[".h2 {font-size: 2.5rem;}"],"settings":{"collection":"flagship-audiophile-headphones","products":[],"full_width":true,"stack_products":false,"show_progress_bar":false,"products_count":2,"products_per_row_mobile":"2","products_per_row_desktop":4,"subheading":"","title":"Flagship Audiophile Headphones","content":"","link_url":"","link_text":"","background":"","background_gradient":"","text_color":"","heading_color":"","heading_gradient":"","product_card_background":"","product_card_text_color":""}},"featured_collection_htGbei":{"type":"featured-collection","custom_css":[".h2 {font-size: 2.5rem;}"],"settings":{"collection":"flagship-audiophile-iems","products":[],"full_width":true,"stack_products":false,"show_progress_bar":false,"products_count":2,"products_per_row_mobile":"2","products_per_row_desktop":4,"subheading":"","title":"Flagship Audiophile IEMs","content":"","link_url":"","link_text":"","background":"","background_gradient":"","text_color":"","heading_color":"","heading_gradient":"","product_card_background":"","product_card_text_color":""}},"featured_collection_NeU94b":{"type":"featured-collection","disabled":true,"custom_css":[".h2 {font-size: 2.5rem;}"],"settings":{"collection":"high-resolution-digital-audio-players-daps","products":[],"full_width":true,"stack_products":false,"show_progress_bar":false,"products_count":4,"products_per_row_mobile":"2","products_per_row_desktop":4,"subheading":"","title":"High-Resolution Digital Audio Players","content":"","link_url":"","link_text":"","background":"","background_gradient":"","text_color":"","heading_color":"","heading_gradient":"","product_card_background":"","product_card_text_color":""}},"featured_collection_bhcL3X":{"type":"featured-collection","custom_css":[".h2 {font-size: 2.5rem;}"],"settings":{"collection":"studio-professional-headphones","products":[],"full_width":true,"stack_products":false,"show_progress_bar":false,"products_count":2,"products_per_row_mobile":"2","products_per_row_desktop":4,"subheading":"","title":"Studio & Professional Headphones","content":"","link_url":"","link_text":"","background":"","background_gradient":"","text_color":"","heading_color":"","heading_gradient":"","product_card_background":"","product_card_text_color":""}},"featured_collection_mciM7V":{"type":"featured-collection","custom_css":[".h2 {font-size: 2.5rem;}"],"settings":{"collection":"on-stage-monitors","products":[],"full_width":true,"stack_products":false,"show_progress_bar":false,"products_count":3,"products_per_row_mobile":"2","products_per_row_desktop":4,"subheading":"","title":"On-Stage Monitors","content":"","link_url":"","link_text":"","background":"","background_gradient":"","text_color":"","heading_color":"","heading_gradient":"","product_card_background":"","product_card_text_color":""}},"featured_collection_BAExpf":{"type":"featured-collection","disabled":true,"custom_css":[".h2 {font-size: 2.5rem;}"],"settings":{"collection":"noise-cancelling-headphones","products":[],"full_width":true,"stack_products":false,"show_progress_bar":false,"products_count":2,"products_per_row_mobile":"2","products_per_row_desktop":4,"subheading":"","title":"Noise Cancelling Headphones","content":"","link_url":"","link_text":"","background":"","background_gradient":"","text_color":"","heading_color":"","heading_gradient":"","product_card_background":"","product_card_text_color":""}},"featured_collection_kQyrCU":{"type":"featured-collection","custom_css":[".h2 {font-size: 2.5rem;}"],"settings":{"collection":"true-wireless-earbuds","products":[],"full_width":true,"stack_products":false,"show_progress_bar":false,"products_count":2,"products_per_row_mobile":"2","products_per_row_desktop":4,"subheading":"","title":"True Wireless Earbuds","content":"","link_url":"","link_text":"","background":"","background_gradient":"","text_color":"","heading_color":"","heading_gradient":"","product_card_background":"","product_card_text_color":""}}},"order":["main","featured_collection_PDEMx6","featured_collection_48GHWB","featured_collection_hMyJJk","featured_collection_eFH8UP","featured_collection_3EzJzq","featured_collection_htGbei","featured_collection_NeU94b","featured_collection_bhcL3X","featured_collection_mciM7V","featured_collection_BAExpf","featured_collection_kQyrCU"]}